{
  "T": 233,
  "status": "OK",
  "min_cost": 670.0,
  "num_diophantine": 2275712,
  "makespan_frequencies": {
    "233": 1,
    "234": 73,
    "235": 1035,
    "236": 6651,
    "237": 26539,
    "238": 75695,
    "239": 164038,
    "240": 279991,
    "241": 383383,
    "242": 425262,
    "243": 382433,
    "244": 276488,
    "245": 157960,
    "246": 69220,
    "247": 21961,
    "248": 4523,
    "249": 446
  },
  "num_meeting_deadline": 1,
  "gantt_files": [
    "gantt_sol001_ms233.png"
  ],
  "elapsed_seconds": 26364.16
}